{
  "uuid": "cc977ffa-9d0d-4b18-a1a6-6913ea71e173",
  "display_id": 161,
  "title": "ferray-stats: reduce_axis_general and _u64 are near-identical duplications",
  "description": "Current state: \n\nDesired state: \n\nReason: \n\nreductions/mod.rs L78-135,433-486: ~100 lines duplicated. Parameterize on output type.",
  "status": "open",
  "priority": "low",
  "created_by": "phase-4-coordinator",
  "created_at": "2026-03-25T15:38:00.234461584Z",
  "updated_at": "2026-03-25T15:38:12.323391288Z",
  "labels": [
    "refactor",
    "qa-audit"
  ]
}